README.md
setup.cfg
setup.py
ghlocalapi/__init__.py
ghlocalapi/alarms.py
ghlocalapi/bluetooth.py
ghlocalapi/device_info.py
ghlocalapi/device_settings.py
ghlocalapi/scan.py
ghlocalapi.egg-info/PKG-INFO
ghlocalapi.egg-info/SOURCES.txt
ghlocalapi.egg-info/dependency_links.txt
ghlocalapi.egg-info/requires.txt
ghlocalapi.egg-info/top_level.txt
ghlocalapi/utils/__init__.py
ghlocalapi/utils/const.py
ghlocalapi/utils/convert.py