Metadata-Version: 2.1
Name: ghlocalapi
Version: 0.3.5
Summary: UNKNOWN
Home-page: https://github.com/ludeeus/ghlocalapi
Author: Joakim Sorensen
Author-email: ludeeus@gmail.com
License: UNKNOWN
Platform: UNKNOWN
Classifier: Programming Language :: Python :: 3
Classifier: License :: OSI Approved :: MIT License
Classifier: Operating System :: OS Independent
